nannyml/__init__.py
nannyml/_typing.py
nannyml/analytics.py
nannyml/base.py
nannyml/calibration.py
nannyml/chunk.py
nannyml/cli/__init__.py
nannyml/cli/cli.py
nannyml/cli/run.py
nannyml/config.py
nannyml/data_quality/__init__.py
nannyml/data_quality/missing/__init__.py
nannyml/data_quality/missing/calculator.py
nannyml/data_quality/missing/result.py
nannyml/data_quality/range/__init__.py
nannyml/data_quality/range/calculator.py
nannyml/data_quality/range/result.py
nannyml/data_quality/unseen/__init__.py
nannyml/data_quality/unseen/calculator.py
nannyml/data_quality/unseen/result.py
nannyml/datasets/__init__.py
nannyml/datasets/data/__init__.py
nannyml/datasets/data/california_housing_analysis.csv
nannyml/datasets/data/california_housing_analysis_gt.csv
nannyml/datasets/data/california_housing_reference.csv
nannyml/datasets/data/employment_MA_analysis.pq
nannyml/datasets/data/employment_MA_analysis_target.pq
nannyml/datasets/data/employment_MA_reference.pq
nannyml/datasets/data/mc_analysis.csv
nannyml/datasets/data/mc_analysis_gt.csv
nannyml/datasets/data/mc_reference.csv
nannyml/datasets/data/regression_synthetic_analysis.csv
nannyml/datasets/data/regression_synthetic_analysis_targets.csv
nannyml/datasets/data/regression_synthetic_reference.csv
nannyml/datasets/data/synthetic_car_loan_analysis.csv
nannyml/datasets/data/synthetic_car_loan_analysis_target.csv
nannyml/datasets/data/synthetic_car_loan_dq_analysis.csv
nannyml/datasets/data/synthetic_car_loan_dq_reference.csv
nannyml/datasets/data/synthetic_car_loan_reference.csv
nannyml/datasets/data/synthetic_sample_analysis.csv
nannyml/datasets/data/synthetic_sample_analysis_gt.csv
nannyml/datasets/data/synthetic_sample_reference.csv
nannyml/datasets/data/titanic_analysis.csv
nannyml/datasets/data/titanic_reference.csv
nannyml/datasets/data/titanic_target.csv
nannyml/datasets/datasets.py
nannyml/distribution/__init__.py
nannyml/distribution/categorical/__init__.py
nannyml/distribution/categorical/calculator.py
nannyml-0.13.1.dist-info/LICENSE
nannyml-0.13.1.dist-info/METADATA
nannyml-0.13.1.dist-info/WHEEL
nannyml-0.13.1.dist-info/entry_points.txt
nannyml-0.13.1.dist-info/RECORD
