Metadata-Version: 2.3
Name: nannyml
Version: 0.13.1
Summary: NannyML, Your library for monitoring model performance.
License: Apache-2.0
Author: Niels Nuyttens
Author-email: niels@nannyml.com
Requires-Python: >=3.9,<3.13
Classifier: Development Status :: 4 - Beta
Classifier: Intended Audience :: Developers
Classifier: License :: OSI Approved :: Apache Software License
Classifier: Natural Language :: English
Classifier: Programming Language :: Python :: 3
Classifier: Programming Language :: Python :: 3.9
Classifier: Programming Language :: Python :: 3.10
Classifier: Programming Language :: Python :: 3.11
Classifier: Programming Language :: Python :: 3.12
Classifier: Programming Language :: Python :: 3.8
Provides-Extra: db
Requires-Dist: APScheduler (>=3.9,<4.0)
Requires-Dist: FLAML[automl] (>=2.3.3,<3.0.0)
Requires-Dist: Jinja2 (>=3.1)
Requires-Dist: PyYAML (>=6.0,<7.0)
Requires-Dist: category-encoders (>=2.3,<3.0)
Requires-Dist: click (>=8.1,<9.0)
Requires-Dist: gcsfs (>=2022.5)
Requires-Dist: joblib (>=1.1,<2.0)
Requires-Dist: kaleido (>=0.2,<0.3)
Requires-Dist: lightgbm (>=3.3,<4.6)
Requires-Dist: matplotlib (>=3.7,<4.0)
Requires-Dist: numpy (>=1.23)
Requires-Dist: pandas (>=1.4)
Requires-Dist: plotly (>=5.6,<6.0)
Requires-Dist: psycopg2-binary (>=2.9,<3.0) ; extra == "db"
Requires-Dist: pyarrow (>=13.0)
Requires-Dist: pydantic (>=2.7)
Requires-Dist: pyfiglet (>=0.8.post1,<0.9)
Requires-Dist: python-dateutil (>=2.8,<3.0)
Requires-Dist: python-dotenv (>=1.0,<2.0)
Requires-Dist: rich (>=12.5)
Requires-Dist: s3fs (>=2022.8)
Requires-Dist: scikit-learn (>=1.3)
Requires-Dist: scipy (>=1.9.2)
Requires-Dist: seaborn (>=0.13,<0.14)
Requires-Dist: segment-analytics-python (>=2.3,<3.0)
Requires-Dist: sqlmodel (>=0.0,<0.1) ; extra == "db"
Project-URL: Homepage, https://github.com/nannyml/nannyml
